compressbins/__init__.py
compressbins/compressbins.py
compressbins-1.2.0.dist-info/LICENSE
compressbins-1.2.0.dist-info/METADATA
compressbins-1.2.0.dist-info/WHEEL
compressbins-1.2.0.dist-info/top_level.txt
compressbins-1.2.0.dist-info/RECORD
