Metadata-Version: 2.1
Name: compressbins
Version: 1.2.0
Summary: Convert numpy bins to a string format ideal for creating frequency charts in the numpy-pandas ecosystem. Ex. [0, 2, 4, 6, 8, 10] -> ['0-2', '2-4', '4-6', '6-8', '8-10'] 
Author-email: Jack Trudan <jackt149@gmail.com>
License: Copyright 2024 Jack Trudan
Project-URL: Homepage, https://github.com/jtrudan/compressbins
Keywords: histograms,stats
Classifier: License :: OSI Approved :: MIT License
Classifier: Programming Language :: Python
Classifier: Programming Language :: Python :: 3
Requires-Python: >=3.9
License-File: LICENSE
Provides-Extra: dev
Requires-Dist: black; extra == "dev"
Requires-Dist: bumpver; extra == "dev"
Requires-Dist: isort; extra == "dev"
Requires-Dist: pip-tools; extra == "dev"
Requires-Dist: pytest; extra == "dev"
Requires-Dist: numpy; extra == "dev"
